mcl/__init__.py
mcl/builder.py
mcl/consts.py
mcl/hook.py
mcl/utils.py
mcl/structures/Fp.py
mcl/structures/Fp2.py
mcl/structures/Fr.py
mcl/structures/G1.py
mcl/structures/G2.py
mcl/structures/GT.py
mcl/structures/__init__.py
mcl/structures/base.py
mcl-0.0.6.dist-info/LICENSE
mcl-0.0.6.dist-info/METADATA
mcl-0.0.6.dist-info/WHEEL
mcl-0.0.6.dist-info/top_level.txt
mcl-0.0.6.dist-info/RECORD
