Metadata-Version: 2.1
Name: mcl
Version: 0.0.6
Summary: Python wrapper for mcl library
Home-page: https://github.com/piotrszyma/mcl-python
Author: Piotr Szyma
Author-email: thompson2908@gmail.com
Classifier: Programming Language :: Python :: 3
Classifier: License :: OSI Approved :: MIT License
Classifier: Operating System :: OS Independent
Requires-Python: >=3.7
License-File: LICENSE
